sphinx_design_elements/__init__.py
sphinx_design_elements/dropdown_group.py
sphinx_design_elements/extension.py
sphinx_design_elements/gridtable.py
sphinx_design_elements/hyper.py
sphinx_design_elements/infocard.py
sphinx_design_elements/shield.py
sphinx_design_elements/tag.py
sphinx_design_elements/compiled/__init__.py
sphinx_design_elements/compiled/addon.js
sphinx_design_elements/compiled/style.css
sphinx_design_elements/util/__init__.py
sphinx_design_elements/util/directive.py
sphinx_design_elements/util/role.py
sphinx_design_elements-0.4.2.dist-info/licenses/LICENSE
sphinx_design_elements-0.4.2.dist-info/METADATA
sphinx_design_elements-0.4.2.dist-info/WHEEL
sphinx_design_elements-0.4.2.dist-info/top_level.txt
sphinx_design_elements-0.4.2.dist-info/RECORD
