Metadata-Version: 2.4
Name: sphinx-design-elements
Version: 0.4.2
Summary: A collection of composite web elements based on components from sphinx-design.
Author-email: Andreas Motl <andreas.motl@panodata.org>
License: MIT License Copyright (c) 2023 Andreas Motl
Project-URL: changelog, https://github.com/tech-writing/sphinx-design-elements/blob/main/CHANGES.md
Project-URL: documentation, https://sphinx-design-elements.readthedocs.io/
Project-URL: homepage, https://sphinx-design-elements.readthedocs.io/
Project-URL: repository, https://github.com/tech-writing/sphinx-design-elements
Keywords: authoring,badge,css,design,documentation,dropdown,extension,flexbox,grid,layout,markdown,material design,myst,responsive html,restructuredtext,shield,sphinx,sphinx design,table,tag,web components
Classifier: Development Status :: 4 - Beta
Classifier: Environment :: Plugins
Classifier: Environment :: Web Environment
Classifier: Framework :: Sphinx
Classifier: Framework :: Sphinx :: Extension
Classifier: Intended Audience :: Customer Service
Classifier: Intended Audience :: Developers
Classifier: Intended Audience :: Education
Classifier: Intended Audience :: End Users/Desktop
Classifier: Intended Audience :: Information Technology
Classifier: Intended Audience :: Manufacturing
Classifier: Intended Audience :: Science/Research
Classifier: Intended Audience :: System Administrators
Classifier: Intended Audience :: Telecommunications Industry
Classifier: License :: OSI Approved :: MIT License
Classifier: Programming Language :: Python :: 3 :: Only
Classifier: Programming Language :: Python :: 3.9
Classifier: Programming Language :: Python :: 3.10
Classifier: Programming Language :: Python :: 3.11
Classifier: Programming Language :: Python :: 3.12
Classifier: Programming Language :: Python :: 3.13
Classifier: Programming Language :: Python :: 3.14
Classifier: Programming Language :: Python :: Implementation :: CPython
Classifier: Topic :: Documentation
Classifier: Topic :: Documentation :: Sphinx
Classifier: Topic :: Education
Classifier: Topic :: File Formats
Classifier: Topic :: Scientific/Engineering
Classifier: Topic :: Software Development :: Bug Tracking
Classifier: Topic :: Software Development :: Code Generators
Classifier: Topic :: Software Development :: Documentation
Classifier: Topic :: Software Development :: Libraries :: Python Modules
Classifier: Topic :: Software Development :: Widget Sets
Classifier: Topic :: Text Processing
Classifier: Topic :: Text Processing :: Markup
Classifier: Topic :: Text Processing :: Markup :: HTML
Classifier: Topic :: Text Processing :: Markup :: Markdown
Classifier: Topic :: Text Processing :: Markup :: reStructuredText
Requires-Python: >=3.9
License-File: LICENSE
Requires-Dist: beautifulsoup4
Requires-Dist: docutils<0.23
Requires-Dist: myst-parser
Requires-Dist: sphinx<10
Requires-Dist: sphinx-design<0.8,>=0.6.1
Requires-Dist: standard-imghdr; python_version >= "3.13"
Provides-Extra: develop
Requires-Dist: black<26; extra == "develop"
Requires-Dist: mypy<1.20; extra == "develop"
Requires-Dist: poethepoet<1; extra == "develop"
Requires-Dist: pyproject-fmt<3; extra == "develop"
Requires-Dist: ruff<0.15; extra == "develop"
Requires-Dist: types-docutils<0.23; extra == "develop"
Requires-Dist: validate-pyproject<1; extra == "develop"
Provides-Extra: docs
Requires-Dist: furo; extra == "docs"
Requires-Dist: myst-parser[linkify]>=0.18; extra == "docs"
Requires-Dist: sphinx-autobuild; extra == "docs"
Requires-Dist: sphinx-copybutton; extra == "docs"
Provides-Extra: release
Requires-Dist: build<2; extra == "release"
Requires-Dist: keyring; extra == "release"
Requires-Dist: twine<7; extra == "release"
Provides-Extra: test
Requires-Dist: pytest<9; extra == "test"
Requires-Dist: pytest-cov<8; extra == "test"
Requires-Dist: pytest-regressions<3; extra == "test"
Requires-Dist: sphinx[test]; extra == "test"
Requires-Dist: sphinx-pytest<0.3; extra == "test"
Requires-Dist: verlib2; extra == "test"
Dynamic: license-file
